./.gitignore
./PKG-INFO
./README.md
./claude.png
./dkb.py
./pyproject.toml
./.github/cliff.toml
./.github/workflows/release.yml
dkb-1.1.1.dist-info/METADATA
dkb-1.1.1.dist-info/WHEEL
dkb-1.1.1.dist-info/entry_points.txt
dkb-1.1.1.dist-info/RECORD
