Metadata-Version: 2.4
Name: dkb
Version: 1.1.1
Summary: Developer Knowledge Base - Fetch and organize documentation locally for vibe coding with Claude Code
Project-URL: Homepage, https://github.com/adriangalilea/dkb
Project-URL: Repository, https://github.com/adriangalilea/dkb
Project-URL: Issues, https://github.com/adriangalilea/dkb/issues
Author-email: Adrian Galilea <adriangalilea@gmail.com>
License: MIT
Keywords: ai,claude-code,developer-tools,documentation,git,knowledge-base,llm,markdown,vibe-coding
Classifier: Development Status :: 3 - Alpha
Classifier: Intended Audience :: Developers
Classifier: License :: OSI Approved :: MIT License
Classifier: Programming Language :: Python :: 3
Classifier: Programming Language :: Python :: 3.12
Classifier: Programming Language :: Python :: 3.13
Classifier: Topic :: Documentation
Classifier: Topic :: Software Development :: Documentation
Classifier: Topic :: Utilities
Requires-Python: >=3.12
Requires-Dist: rich>=14.0.0
Provides-Extra: dev
Requires-Dist: ruff; extra == 'dev'
